awsctl/__init__.py
awsctl/cli.py
awsctl/commands/__init__.py
awsctl/commands/install.py
awsctl/packages/__init__.py
awsctl/packages/cloudwatch.py
awsctl/packages/common.py
awsctl/packages/inspector.py
awsctl/packages/ssm.py
awsctl_cli-0.4.0.dist-info/LICENSE
awsctl_cli-0.4.0.dist-info/METADATA
awsctl_cli-0.4.0.dist-info/WHEEL
awsctl_cli-0.4.0.dist-info/entry_points.txt
awsctl_cli-0.4.0.dist-info/top_level.txt
awsctl_cli-0.4.0.dist-info/RECORD
