Metadata-Version: 2.1
Name: awsctl-cli
Version: 0.4.0
Summary: A simple tool to install AWS agents and packages.
Home-page: https://github.com/arhea/awsctl
Author: Alex Rhea
Author-email: alex.rhea@gmail.com
License: UNKNOWN
Platform: UNKNOWN
Classifier: Environment :: Console
Classifier: License :: OSI Approved :: Apache Software License
Classifier: Operating System :: POSIX :: Linux
Classifier: Programming Language :: Python
Classifier: Programming Language :: Python :: 3
Classifier: Programming Language :: Python :: 3.6
Classifier: Programming Language :: Python :: 3.7
Classifier: Programming Language :: Python :: Implementation :: CPython
Classifier: Programming Language :: Python :: Implementation :: PyPy
Requires-Python: >=3.7.0
Requires-Dist: click
Requires-Dist: colorama
Requires-Dist: requests
